{
  "indexes": [
    {
      "collectionGroup": "posts",
      "queryScope": "COLLECTION",
      "fields": [
        { "fieldPath": "authorId", "order": "ASCENDING" },
        { "fieldPath": "createdAt", "order": "DESCENDING" }
      ]
    },
    {
      "collectionGroup": "projects",
      "queryScope": "COLLECTION",
      "fields": [
        { "fieldPath": "teamMemberIds", "arrayConfig": "CONTAINS" },
        { "fieldPath": "createdAt", "order": "DESCENDING" }
      ]
    },
    {
      "collectionGroup": "projectInvitations",
      "queryScope": "COLLECTION",
      "fields": [
        { "fieldPath": "recipientId", "order": "ASCENDING" },
        { "fieldPath": "sentAt", "order": "DESCENDING" }
      ]
    },
    {
      "collectionGroup": "ndaInvitations",
      "queryScope": "COLLECTION",
      "fields": [
        { "fieldPath": "recipientId", "order": "ASCENDING" },
        { "fieldPath": "status", "order": "ASCENDING" }
      ]
    }
  ],
  "fieldOverrides": []
}
